cfelpyutils/__init__.py
cfelpyutils/calibration.py
cfelpyutils/crystfel_stream.py
cfelpyutils/geometry/__init__.py
cfelpyutils/geometry/crystfel_utils.py
cfelpyutils/geometry/geometry.py
cfelpyutils/geometry/named_tuples.py
cfelpyutils/peakfinding/__init__.py
cfelpyutils/peakfinding/peakfinder8.py
cfelpyutils/peakfinding/lib/__init__.py
cfelpyutils/peakfinding/lib/peakfinder8_extension.cpython-310-x86_64-linux-gnu.so
cfelpyutils-2.2.0.data/data/data/peakfinder8_extension.pyx
tests/__init__.py
tests/fixtures.py
tests/calibration/__init__.py
tests/calibration/test_calibration.py
tests/crystfel_stream/__init__.py
tests/crystfel_stream/test_crystfel_stream.py
tests/geometry/__init__.py
tests/geometry/test_crystfel_utils.py
tests/geometry/test_geometry.py
tests/peakfinding/__init__.py
tests/peakfinding/test_init.py
tests/peakfinding/test_peakfinder8.py
cfelpyutils-2.2.0.dist-info/LICENSE
cfelpyutils-2.2.0.dist-info/METADATA
cfelpyutils-2.2.0.dist-info/WHEEL
cfelpyutils-2.2.0.dist-info/top_level.txt
cfelpyutils-2.2.0.dist-info/RECORD
