Metadata-Version: 2.4
Name: cfelpyutils
Version: 2.2.0
Summary: Utility functions and classes for CFEL software projects
Home-page: https://gitlab.desy.de/cfel-sc-public/cfelpyutils
Author: Coherent Imaging Division, CFEL
Author-email: sc@cfel.de
License: GNU General Public License v3.0
Platform: unix
Platform: linux
Platform: osx
Platform: cygwin
Platform: win32
Classifier: Programming Language :: Python :: 3
Classifier: Programming Language :: Python :: 3 :: Only
Classifier: Programming Language :: Python :: 3.9
Classifier: Programming Language :: Python :: 3.10
Classifier: Programming Language :: Python :: 3.11
Classifier: Programming Language :: Python :: 3.12
Classifier: License :: OSI Approved :: GNU General Public License v3 or later (GPLv3+)
Classifier: Natural Language :: English
Classifier: Intended Audience :: Science/Research
License-File: LICENSE
Requires-Dist: h5py>=2.9.0
Requires-Dist: mypy-extensions>=0.4.3
Requires-Dist: numpy>=1.16.4
Requires-Dist: pandas>=1.1.5
Requires-Dist: typing>=3.6.4; python_version < "3.7"
Dynamic: license-file
